GoogleTransAPI/__init__.py
GoogleTransAPI/googleTranApi.py
GoogleTransAPI-1.0.0.dist-info/LICENSE
GoogleTransAPI-1.0.0.dist-info/METADATA
GoogleTransAPI-1.0.0.dist-info/WHEEL
GoogleTransAPI-1.0.0.dist-info/top_level.txt
GoogleTransAPI-1.0.0.dist-info/RECORD
