Metadata-Version: 2.1
Name: GoogleTransAPI
Version: 1.0.0
Summary: A package that inputs Japanese and output Mp3 by google translate
Home-page: https://github.com/YungfeiLi/GoogleTranApi.git
Author: YunfeiLi
Author-email: UNKNOWN
License: UNKNOWN
Platform: UNKNOWN
Classifier: Programming Language :: Python :: 3
Classifier: License :: OSI Approved :: MIT License
Classifier: Operating System :: OS Independent
